annorest/API.py
annorest/__init__.py
annorest/cc.py
annorest/database.py
annorest/kshot.py
annorest/loader.py
annorest/utils.py
annorest-0.1.0.dist-info/LICENSE
annorest-0.1.0.dist-info/METADATA
annorest-0.1.0.dist-info/WHEEL
annorest-0.1.0.dist-info/top_level.txt
annorest-0.1.0.dist-info/RECORD
